{
  "collapse-filter": true,
  "search": "",
  "showTags": true,
  "showAttachments": false,
  "hideUnresolved": false,
  "showOrphans": true,
  "collapse-color-groups": true,
  "colorGroups": [],
  "collapse-display": false,
  "showArrow": false,
  "textFadeMultiplier": -1.6,
  "nodeSizeMultiplier": 1.49088541666667,
  "lineSizeMultiplier": 1.60572916666667,
  "collapse-forces": true,
  "centerStrength": 0.536458333333333,
  "repelStrength": 11.1458333333333,
  "linkStrength": 0.848958333333333,
  "linkDistance": 155,
  "scale": 0.27268599173601116,
  "close": true
}